{
  "global": {
    "poizon": {
      "bg": {
        "value": "linear-gradient(101deg, #000 0%, #1D3337 50%, #0FF 100%)",
        "type": "color"
      },
      "color": {
        "value": "#fff",
        "type": "color"
      }
    },
    "iherb": {
      "bg": {
        "value": "#458500",
        "type": "color"
      },
      "color": {
        "value": "#fff",
        "type": "color"
      }
    },
    "amazon": {
      "bg": {
        "value": "linear-gradient(101deg, #000 0%, #000 50%, #F90 100%)",
        "type": "color"
      },
      "color": {
        "value": "#fff",
        "type": "color"
      }
    },
    "trendyol": {
      "bg": {
        "value": "#FF6720",
        "type": "color"
      },
      "color": {
        "value": "#fff",
        "type": "color"
      }
    },
    "macys": {
      "bg": {
        "value": "#E2192C",
        "type": "color"
      },
      "color": {
        "value": "#fff",
        "type": "color"
      }
    },
    "ebay": {
      "bg": {
        "value": "linear-gradient(90deg, #E43137 -0.94%, #E43137 24.21%, #0063D1 24.21%, #0063D1 49.36%, #F4AE01 49.37%, #F4AE01 74.52%, #85B716 74.52%, #85B716 99.67%)",
        "type": "color"
      },
      "color": {
        "value": "#fff",
        "type": "color"
      }
    },
    "zara": {
      "bg": {
        "value": "#fff",
        "type": "color"
      },
      "color": {
        "value": "#000",
        "type": "color"
      }
    },
    "handm": {
      "bg": {
        "value": "#c6071d",
        "type": "color"
      },
      "color": {
        "value": "#fff",
        "type": "color"
      }
    }
  },
  "$themes": [],
  "$metadata": {
    "tokenSetOrder": [
      "global"
    ]
  }
}